pypolona/__init__.py
pypolona/__main__.py
pypolona/polona.py
pypolona-1.6.0.dist-info/LICENSE
pypolona-1.6.0.dist-info/METADATA
pypolona-1.6.0.dist-info/WHEEL
pypolona-1.6.0.dist-info/entry_points.txt
pypolona-1.6.0.dist-info/top_level.txt
pypolona-1.6.0.dist-info/RECORD
