Metadata-Version: 2.1
Name: pypolona
Version: 1.6.0
Summary: Image downloader for the polona.pl website of the Polish National Library
Home-page: https://twardoch.github.io/pypolona/
Author: Adam Twardoch
Author-email: adam+github@twardoch.com
License: MIT
Project-URL: Source, https://github.com/twardoch/pypolona
Keywords: polona jpeg downloader cli
Platform: UNKNOWN
Classifier: Environment :: Console
Classifier: Development Status :: 4 - Beta
Classifier: License :: OSI Approved :: MIT License
Classifier: Programming Language :: Python :: 3.7
Requires-Python: >=3.7
Requires-Dist: Gooey (>=1.0.4)
Requires-Dist: colored (>=1.4.2)
Requires-Dist: ezgooey (>=1.3.2)
Requires-Dist: html2text (>=2020.1.16)
Requires-Dist: img2pdf (>=0.4.0)
Requires-Dist: lxml2json (>=0.2.6)
Requires-Dist: lxml (>=4.5.2)
Requires-Dist: orderedattrdict (>=1.6.0)
Requires-Dist: pikepdf (>=1.19.3)
Requires-Dist: python-dateutil (>=2.8.1)
Requires-Dist: yaplon (>=1.2.4)
Requires-Dist: pywin32 (>=228) ; sys_platform == "win32"
Provides-Extra: dev
Requires-Dist: twine (>=3.2.0) ; extra == 'dev'
Requires-Dist: pyinstaller (>=4.0) ; extra == 'dev'
Requires-Dist: dmgbuild (>=1.3.3) ; (sys_platform == "darwin") and extra == 'dev'
